DBTron/__init__.py
DBTron/mongoDBOps.py
DBTron/sqlOps.py
DBTron-0.0.5.dist-info/LICENCE
DBTron-0.0.5.dist-info/METADATA
DBTron-0.0.5.dist-info/WHEEL
DBTron-0.0.5.dist-info/top_level.txt
DBTron-0.0.5.dist-info/RECORD
