Metadata-Version: 2.1
Name: DBTron
Version: 0.0.5
Summary: A Package Which allows to access and perform Operations on Different Relational and Non-Relational DataBases 
Home-page: UNKNOWN
Author: Suraj Jaiswal
Author-email: <surajaiswal13@gmail.com>
License: MIT
Platform: UNKNOWN
Classifier: Development Status :: 1 - Planning
Classifier: Intended Audience :: Developers
Classifier: Programming Language :: Python :: 3
Classifier: Operating System :: Unix
Classifier: Operating System :: MacOS :: MacOS X
Classifier: Operating System :: Microsoft :: Windows
Requires-Dist: flask
Requires-Dist: pandas
Requires-Dist: pymongo
Requires-Dist: mysql-connector-python
Requires-Dist: pymongo[srv]
